reconstructor/__init__.py
reconstructor/__main__.py
reconstructor/_funcs.py
reconstructor/build.py
reconstructor/diamond.exe
reconstructor-1.1.2.dist-info/LICENSE
reconstructor-1.1.2.dist-info/METADATA
reconstructor-1.1.2.dist-info/WHEEL
reconstructor-1.1.2.dist-info/RECORD
