Metadata-Version: 2.1
Name: reconstructor
Version: 1.1.2
Summary: COBRApy Compatible Genome Scale Metabolic Network Reconstruction Tool: Reconstructor
License: MIT
Author: Matt Jenior and Emma Glass
Requires-Python: >=3.8,<3.11
Classifier: License :: OSI Approved :: MIT License
Classifier: Programming Language :: Python :: 3
Classifier: Programming Language :: Python :: 3.8
Classifier: Programming Language :: Python :: 3.9
Classifier: Programming Language :: Python :: 3.10
Requires-Dist: cobra (>0.22.1,<0.24)
Requires-Dist: numpy (<1.24)
Requires-Dist: symengine (>=0.9.2,<0.10.0)
Requires-Dist: unipath (==1.1)
Requires-Dist: wget (>=3.2,<4.0)
